MANIFEST.in
setup.py
taco.py
tableconv/__init__.py
tableconv/converters.py
tableconv/types.py
tableconv/templates/tex/layout.jinja2
tableconv/templates/tex/list.jinja2
tableconv/templates/tex/table.jinja2
tableconv/templates/txt/layout.jinja2
tableconv/templates/txt/list.jinja2
tableconv/templates/txt/table.jinja2
taco.py.egg-info/PKG-INFO
taco.py.egg-info/SOURCES.txt
taco.py.egg-info/dependency_links.txt
taco.py.egg-info/not-zip-safe
taco.py.egg-info/requires.txt
taco.py.egg-info/top_level.txt